tbgdl/__init__.py
TBGDL-1.0.3.dist-info/LICENSE
TBGDL-1.0.3.dist-info/METADATA
TBGDL-1.0.3.dist-info/WHEEL
TBGDL-1.0.3.dist-info/top_level.txt
TBGDL-1.0.3.dist-info/RECORD
