Metadata-Version: 2.1
Name: TBGDL
Version: 1.0.3
Summary: A Python library for creating text-based games.
Home-page: https://github.com/Marko2155/TBGDL
Author: Marko Camandioti
Author-email: camandiotimarko@gmail.com
License: MIT
Project-URL: Documentation, https://github.com/Marko2155/TBGDL#readme
Project-URL: Source, https://github.com/Marko2155/TBGDL
Project-URL: Tracker, https://github.com/Marko2155/TBGDL/issues
Keywords: pygame,textadventure,text,game
License-File: LICENSE
Requires-Dist: colorama
Requires-Dist: simpleaudio
Requires-Dist: numpy
Requires-Dist: musicalbeeps
